{
  "id": "lv-law-50689",
  "type": "statute",
  "title": "Par akcīzes nodokli alkoholiskajiem dzērieniem",
  "short_name": "TA-50689",
  "status": "in_force",
  "url": "https://likumi.lv/ta/id/50689-par-akcizes-nodokli-alkoholiskajiem-dzerieniem",
  "description": "Official consolidated text from Likumi.lv (Latvijas Vēstnesis).",
  "provisions": [
    {
      "provision_ref": "Art. 1",
      "chapter": "I nodaļa. Vispārīgie noteikumi",
      "section": "1",
      "title": "Likumā lietotie termini",
      "content": "(1) Likumā lietotie termini atbilst likumā \"Par nodokļiem un nodevām\", Muitas likumā un likumā \" Par muitas nodokli (tarifiem) \" lietotajiem terminiem, ja šajā likumā nav noteikts citādi.\n(2) Likumā ir lietoti arī šādi termini:\n1) alkoholiskie dzērieni — vīns, raudzētie dzērieni, starpprodukti un pārējie alkoholiskie dzērieni, kas minēti šīs daļas 5.punktā ;\n2) vīns:\na) negāzēts vīns — produkts, kurš atbilst Latvijas kombinētās nomenklatūras kodiem 2204 un 2205, ja vien tas iegūts, raudzējot dabīgos vīna materiālus, un faktiskais spirta daudzums tajā pārsniedz 1,2 tilpumprocentus, bet nepārsniedz 18 tilpumprocentus un ja galaproduktā esošais spirts radies vienīgi rūgšanas procesā,\nb) dzirkstošais vīns — produkts, kurš atbilst Latvijas kombinētās nomenklatūras kodiem 2204 un 2205, ja vien tas iegūts, raudzējot dabīgos vīna materiālus, un faktiskais spirta daudzums tajā pārsniedz 1,2 tilpumprocentus, bet nepārsniedz 15 tilpumprocentus un ja galaproduktā esošais spirts radies vienīgi rūgšanas procesā. Produkts ir ar virsspiedienu šķidrumā (trīs bāri vai vairāk) oglekļa dioksīda klātbūtnes dēļ, un tas iepildīts pudelēs ar īpaši nostiprinātiem galviņkorķiem vai citā iepakojumā;\n3) raudzētie dzērieni:\na) negāzēti raudzētie dzērien i — produkti (izņemot vīnu), kuri atbilst Latvijas kombinētās nomenklatūras kodiem 2204, 2205 un 2206, ja vien faktiskais spirta daudzums tajos pārsniedz 1,2 tilpumprocentus, bet nepārsniedz 15 tilpumprocentus un ja galaproduktā esošais spirts radies vienīgi rūgšanas procesā,\nb) dzirkstošie raudzētie dzērien i — produkti (izņemot vīnu), kuri atbilst Latvijas kombinētās nomenklatūras kodiem 2204, 2205 un 2206, ja vien faktiskais spirta daudzums tajos pārsniedz 1,2 tilpumprocentus, bet nepārsniedz 15 tilpumprocentus un ja galaproduktā esošais spirts radies vienīgi rūgšanas procesā. Produkti ir ar virsspiedienu šķidrumā (trīs bāri vai vairāk) oglekļa dioksīda klātbūtnes dēļ, un tie iepildīti pudelēs ar īpaši nostiprinātiem galviņkorķiem vai citā iepakojumā;\n4) starpprodukti — produkti (izņemot vīnu un raudzētos dzērienus), kuri atbilst Latvijas kombinētās nomenklatūras kodiem 2204, 2205 un 2206, ja vien to pamatizejviela ir vīns vai raudzētie dzērieni un faktiskais spirta daudzums tajos pārsniedz 1,2 tilpumprocentus, bet nepārsniedz 22 tilpumprocentus. Gatavā starpprodukta sastāvā esošais spirts var nebūt tikai raudzētas izcelsmes, ja vismaz 30 procenti no faktiskā spirta daudzuma tilpumprocentiem ir raudzētas izcelsmes;\n5) pārējie alkoholiskie dzērieni:\na) spirts — produkts, kurš atbilst Latvijas kombinētās nomenklatūras kodiem 2207, 220890910 un 220890990,\nb) produkti, kuri atbilst Latvijas kombinētās nomenklatūras kodam 2208, izņemot spirtu,\nc) produkti, kuri atbilst Latvijas kombinētās nomenklatūras kodiem 2204, 2205 un 2206, bet neatbilst šīs daļas 2. , 3. un 4.punktā minētajiem nosacījumiem,\nd) jebkuri citi pārtikas produkti, kuros faktiskā spirta daudzums pārsniedz 1,2 tilpumprocentus, izņemot tos, kuri minēti šīs daļas 2. , 3. un 4.punktā un šā punkta “a”, “b” un “c” apakšpunktā;\n6) akcīzes nodokļa marka — Valsts ieņēmumu dienesta izdota īpaša alkoholisko dzērienu akcīzes nodokļa marka, kas tiek piestiprināta alkoholisko dzērienu pudelei (vai citam fasējumam) un apliecina, ka ar akcīzes nodokļa markām marķētie alkoholiskie dzērieni ir ņemti valsts kontrolē a t bilstoši alkoholiskajiem dzērieniem noteiktā akcīzes nodokļa samaksas nosacījumiem un alkoholiskajiem dzērieniem ir legāla izcelsme;\n7) akcīzes preču noliktava — alkoholisko dzērienu akcīzes preču noliktava — Valsts ieņēmumu dienesta kontrolēta vieta, kur noliktavas turētājs ražo, pārstrādā, uzglabā, ieved, saņem vai nosūta alkoholiskos dzērienus, piemērojot atlikto nodokļa maksāšanu saskaņā ar šā likuma nosacījumiem;\n8) noliktavas turētājs — akcīzes preču noliktavas turētājs — juridiskā persona, kurai ir Valsts ieņēmumu dienesta atļauja turēt akcīzes preču noliktavu un kuras īpašumā vai valdījumā ir akcīzes preču noliktava;\n9) licencēts importētājs — juridiskā persona, kura Alkohola aprites likumā noteiktajā kārtībā saņēmusi speciālu atļauju (licenci) alkoholisko dzērienu ievešanai Latvijas Republikas muitas teritorijā izlaišanai brīvam apgrozījumam un kurai nav noliktavas turētāja statusa;\n10) atliktā nodokļa maksāšana — akcīzes nodokļa samaksas atlikšana, ievērojot šā likuma nosacījumus attiecībā uz alkoholisko dzērienu ražošanu, pārstrādi, uzglabāšanu un pārvadāšanu."
    },
    {
      "provision_ref": "Art. 2",
      "chapter": "I nodaļa. Vispārīgie noteikumi",
      "section": "2",
      "title": "Likuma darbības sfēra",
      "content": "(1) Šis likums attiecas uz alkoholiskajiem dzērieniem, kurus ražo, pārstrādā, glabā, realizē, saņem vai nosūta Latvijas Republikas muitas teritorijā, un nosaka kārtību, kādā alkoholiskie dzērieni tiek aplikti ar akcīzes nodokli (turpmāk — nodoklis).\n(2) Kārtību, kādā veicama uzņēmējdarbība ar alkoholiskajiem dzērieniem Latvijas Republikas muitas teritorijā (ražošana, pārstrādāšana, pārvadāšana, glabāšana, ievešana, izvešana, realizācija), nosaka likumi un Ministru kabineta noteikumi.\n(3) Likums neattiecas uz produktiem, kuriem piemēro akcīzes nodokli saskaņā ar likumu “ Par akcīzes nodokli alum”."
    },
    {
      "provision_ref": "Art. 3",
      "chapter": "I nodaļa. Vispārīgie noteikumi",
      "section": "3",
      "title": "Ar nodokli apliekamais objekts",
      "content": "(1) Ar nodokli apliekamais objekts ir šādi alkoholiskie dzērieni:\n1) vīns;\n2) raudzētie dzērieni;\n3) starpprodukti;\n4) (izslēgts ar 12.12.2002 . likumu) ;\n5) pārējie alkoholiskie dzērieni.\n(2) (Izslēgta ar 12.12.2002 . likumu)"
    },
    {
      "provision_ref": "Art. 4",
      "chapter": "I nodaļa. Vispārīgie noteikumi",
      "section": "4",
      "title": "Nodokļa maksātāji",
      "content": "Nodokļa maksātāji ir:\n1) fiziskās vai juridiskās personas vai ar līgumu vai norunu saistītas fizisko vai juridisko personu grupas, kas alkoholiskos dzērienus ieved Latvijas Republikas muitas teritorijā izlaišanai brīvam apgrozījumam;\n2) noliktavas turētāji šajā likumā noteiktajos gadījumos;\n3) citas personas saskaņā ar šā likuma 16.pantu ."
    },
    {
      "provision_ref": "Art. 5",
      "chapter": "I nodaļa. Vispārīgie noteikumi",
      "section": "5",
      "title": "Alkoholisko dzērienu marķēšana",
      "content": "(1) Visi alkoholiskie dzērieni ir marķējami ar akcīzes nodokļa markām, izņemot šā panta ceturtajā daļā noteiktos gadījumus.\n(2) Ar akcīzes nodokļa markām atļauts marķēt alkoholiskos dzērienus:\n1) Latvijas Republikas muitas teritorijā — tikai akcīzes preču noliktavās vai muitas noliktavās, ja saņemta Valsts ieņēmumu dienesta atļauja;\n2) ārvalstīs — ievešanai Latvijas Republikas muitas teritorijā.\n(3) Kārtību, kādā alkoholiskie dzērieni marķējami ar akcīzes nodokļa markām, nosaka Ministru kabinets.\n(4) Nemarķēt ar akcīzes nodokļa markām atļauts:\n1) alkoholiskos dzērienus:\na) \"Rīgas melno balzamu\", kas iepildīts māla krūkās,\nb) alkoholiskos dzērienus, kuri iepildīti pudelēs ar tilpumu līdz 100 mililitriem,\nc) alkoholiskos dzērienus, kuri atbrīvoti no nodokļa saskaņā ar šā likuma 8.panta pirmo daļu vai kuriem piemēro nodokli saskaņā ar šā likuma 8.panta ceturto daļu,\nd) vīnu, kuru fiziskā persona ieved Latvijas Republikas muitas teritorijā savam patēriņam;\n2) alkoholiskos dzērienus, kurus uzglabā, pārvieto vai realizē:\na) akcīzes preču noliktavās,\nb) Muitas likumā un normatīvajos aktos noteiktajās vietās, kur alkoholiskos dzērienus atļauts uzglabāt un realizēt, nemaksājot nodokli,\nc) saskaņā ar šā likuma 15.pantu ."
    },
    {
      "provision_ref": "Art. 6",
      "chapter": "I nodaļa. Vispārīgie noteikumi",
      "section": "6",
      "title": "Akcīzes preču noliktava",
      "content": "(1) Alkoholisko dzērienu ražošana, pārstrāde un fasēšana atļauta tikai akcīzes preču noliktavā.\n(1 1 ) Visiem alkoholiskajiem dzērieniem, kuri atrodas akcīzes preču noliktavā, piemēro atlikto nodokļa maksāšanu līdz brīdim, kad par tiem ir samaksāts nodoklis vai tie ir atbrīvoti no nodokļa maksāšanas saskaņā ar šo likumu.\n(2) Alkoholisko dzērienu uzglabāšana, piemērojot atlikto nodokļa maksāšanu, atļauta tikai akcīzes preču noliktavā, izņemot Muitas likumā noteiktos gadījumus.\n(3) Noliktavas turētājs atbild par visiem alkoholiskajiem dzērieniem, kuri tiek novietoti akcīzes preču noliktavā, kā arī uzskaita un reģistrē jebkuras darbības ar alkoholiskajiem dzērieniem šajā akcīzes preču noliktavā.\n(4) Lai izveidotu un turētu akcīzes preču noliktavu, iesniedzams šā likuma 14.pantā noteiktais vispārējais nodrošinājums.\n(5) Kārtību, kādā atļauts izveidot un turēt akcīze s preču noliktavu, nosaka Ministru kabinets."
    },
    {
      "provision_ref": "Art. 7",
      "chapter": "I nodaļa. Vispārīgie noteikumi",
      "section": "7",
      "title": "Nodokļa likmes un to piemērošana",
      "content": "(1) Alkoholiskajiem dzērieniem nodokli aprēķina pēc šādām likmēm:\n1) vīnam (par 100 litriem) — 30 latu;\n2) pārējiem raudzētajiem dzērieniem (par 100 litriem) — 30 latu;\n3) starpproduktiem (par 100 litriem):\na) ar absolūtā spirta saturu līdz 15 tilpumprocentiem (ieskaitot) — 42 lati,\nb) ar absolūtā spirta saturu virs 15 tilpumprocentiem līdz 22 tilpumprocentiem (ieskaitot) — 70 latu;\n4) (izslēgts ar 12.12.2002 . likumu) ;\n5) pārējiem alkoholiskajiem dzērieniem (par 100 litriem absolūtā spirta) — 550 latu.\n(2) Aprēķinot nodokli, šā panta pirmās daļas 5.punktā minēto alkoholisko dzērienu daudzums litros Ministru kabineta noteiktajā kārtībā nosakāms atbilstoši to daudzumam 20 grādu temperatūrā pēc Celsija.\n(3) Vīnam, kuru fiziskā persona ieved Latvijas Republikas muitas teritorijā savam patēriņam virs šā likuma 8.panta pirmās daļas 7.punkta “a” apakšpunktā noteiktā daudzuma, nodokļa likmi nosaka divkāršā apmērā no šā panta pirmās daļas 1.punktā minētās nodokļa likmes."
    },
    {
      "provision_ref": "Art. 8",
      "chapter": "II nodaļa. Atbrīvojumi un atvieglojumi",
      "section": "8",
      "title": "Atbrīvojumi",
      "content": "(1) No nodokļa ir atbrīvoti:\n1) denaturēti alkoholiskie dzērieni;\n2) alkoholiskie dzērieni, kurus izmanto alkoholisko dzērienu kvalitātes noteikšanai;\n3) alkoholiskie dzērieni, kas zuduši nepārvaramas varas dēļ;\n4) spirts medicīnas, veterinārmedicīnas un farmaceitiskās rūpniecības vajadzībām;\n5) spirts, ja minētajos gadījumos nevar izmantot denaturētu spirtu:\na) ko izmanto zinātniskās pētniecības vajadzībām,\nb) ko izmanto citu produktu vai preču (izņemot alkoholisko dzērienu) kvalitātes noteikšanai,\nc) kas kā neatņemama sastāvdaļa ietilpst ierīcēs un mehānismos vai nodrošina ierīču un mehānismu darbību,\nd) ko izmanto kosmētikas līdzekļu ražošanā;\n6) vīns vai raudzētie dzērieni, kurus izgatavojusi fiziskā persona savam patēriņam;\n7) alkoholiskie dzērieni, kurus fiziskā persona Latvijas Republikas muitas teritorijā ieved savam patēriņam šādā apjomā:\na) negāzēts vīns — līdz diviem litriem,\nb) starpprodukti, raudzētie dzērieni un dzirkstošie vīni — līdz diviem litriem vai citi alkoholiskie dzērieni — līdz vienam litram,\nc) minētie alkoholiskie dzērieni sortimentā — proporcionāli nepārsniedzot iepriekšminēto atļauto daudzumu;\n8) alkoholiskie dzērieni, ko satur šokolādes produkti vai citi pārtikas produkti, ievērojot šā panta trešās daļas nosacījumus;\n9) spirts, ko satur etiķis vai citi produkti, kas atbilst Latvijas kombinētās nomenklatūras kodam 2209;\n10) spirts, ko satur produkti, kas atbilst Latvijas kombinētās nomenklatūras kodiem 2106 un 3302 un kas domāti tādu pārtikas produktu vai bezalkoholisko dzērienu izgatavošanai, kuros faktiskais spirta daudzums nepārsniedz 1,2 tilpumprocentus;\n11) produkti, kuri atbilst pārējo alkoholisko dzērienu definīcijai un kurus iznīcina, denaturē vai kā citādi nodrošina, lai tie nebūtu lietojami uzturā vai izmantojami alkoholisko dzērienu vai citu uzturā lietojamu produktu ražošanā.\n(2) Kārtību, kādā denaturējami alkoholiskie dzērieni, nosaka Ministru kabinets.\n(3) Šā panta pirmās daļas 8.punktā minētais nodokļa atbrīvojums piemērojams alkoholiskajiem dzērieniem, ja spirta saturs nepārsniedz 8,5 litrus absolūtā spirta 100 kilogramos šokolādes produktu vai 5 litrus absolūtā spirta 100 kilogramos citu pārtikas produktu.\n(4) Ja šā panta trešās daļas nosacījumi netiek ievēroti, minētajiem alkoholiskajiem dzērieniem aprēķina nodokli par visu izmantotā spirta daudzumu pēc šā likuma 7.panta pirmajā daļā noteiktajām nodokļa likmēm.\n(5) Kārtību, kādā piemēro šā panta pirmās daļas 5., 8., 9., 10. un 11.punktā noteiktos nodokļa atbrīvojumus, nosaka Ministru kabinets."
    },
    {
      "provision_ref": "Art. 9",
      "chapter": "II nodaļa. Atbrīvojumi un atvieglojumi",
      "section": "9",
      "title": "Atvieglojumi",
      "content": "(Izslēgts ar 12.12.2002 . likumu, kas stājas spēkā 01.01.2003. )"
    },
    {
      "provision_ref": "Art. 10",
      "chapter": "III nodaļa. Nodokļa aprēķināšana un maksāšana",
      "section": "10",
      "title": "Nodokļa aprēķināšana",
      "content": "Nodokli aprēķina pēc šā likuma 7.pantā noteiktajām likmēm alkoholiskajiem dzērieniem:\n1) kurus ieved Latvijas Republikas muitas teritorijā;\n2) kurus izved no akcīzes preču noliktavas;\n3) kurus nepieciešams marķēt ar akcīzes nodokļa markām, saņemot akcīzes nodokļa markas;\n4) kuriem piemēro atlikto nodokļa maksāšanu;\n5) kurus patērē akcīzes preču noliktavā (tajā skaitā prezentācijās, izstādēs, degustācijās, izņemot alkoholisko dzērienu ražošanu);\n6) kurus konstatē kā pārpalikumu vai iztrūkumu akcīzes preču noliktavā;\n7) kurus konstatē kā iztrūkumu (izlaupījumu, zaudējumu, zudumu u.c.) šā likuma 15. vai 15. 1 pantā minētajos gadījumos;\n8) kuriem piemēro nodokli saskaņā ar Muitas likumu vai citiem attiecīgiem normatīvajiem aktiem;\n9) kurus apliek ar nodokli saskaņā ar šā likuma 16.pantu ."
    },
    {
      "provision_ref": "Art. 11",
      "chapter": "III nodaļa. Nodokļa aprēķināšana un maksāšana",
      "section": "11",
      "title": "Nodokļa maksāšana",
      "content": "(1) Nodokļa taksācijas periods ir viens kalendāra mēnesis.\n(2) Nodokļa maksāšanai drīkst izmantot tikai bezskaidras naudas norēķinus. Nodokļa maksāšanai par vīnu, kuru fiziskā perona ieved savam patēriņam, drīkst izmantot arī skaidrās naudas norēķinus.\n(3) Licencēts importētājs vai noliktavas turētājs nodokli par alkoholiskajiem dzērieniem, ja šajā likumā nav noteikts citādi, maksā vienā no šādiem gadījumiem:\n1) pirms akcīzes nodokļa marku saņemšanas;\n2) par taksācijas periodā saņemtajām akcīzes nodokļa markām 15 dienu laikā pēc taksācijas perioda beigām.\n(4) Nodokļa maksātājs aprēķināto nodokli par šā likuma 5.panta ceturtās daļas 1.punkta “a”, “b” un “d” apakšpunktā minētajiem alkoholiskajiem dzērieniem, kuri no ārvalstīm ievesti Latvijas Republikas muitas teritorijā izlaišanai brīvam apgrozījumam, samaksā kredītiestādē pirms alkoholisko dzērienu uzrādīšanas muitas iestādē, ja šajā likumā nav noteikts citādi.\n(5) Noliktavas turētājs taksācijas periodā aprēķināto nodokli par šā likuma 5.panta ceturtās daļas 1.punkta \"a\", \"b\" un \"d\" apakšpunktā minētajiem alkoholiskajiem dzērieniem, kuri taksācijas periodā izvesti no akcīzes preču noliktavas, iemaksā valsts budžetā 15 dienu laikā pēc taksācijas perioda beigām, ja šajā likumā nav noteikts citādi.\n(6) Noliktavas turētājs nodokli par taksācijas periodā konstatēto alkoholisko dzērienu pārpalikumu vai iztrūkumu akcīzes preču noliktavā iemaksā valsts budžetā, ievērojot šā likuma 17.panta noteikumus.\n(7) Noliktavas turētājs nodokli par alkoholiskajiem dzērieniem, kas taksācijas periodā patērēti akcīzes preču noliktavā (tajā skaitā prezentācijās, izstādēs, degustācijās, izņemot alkoholisko dzērienu ražošanu), iemaksā valsts budžetā 15 dienu laikā pēc taksācijas perioda beigām, ja šajā likumā nav noteikts citādi.\n(8) Noliktavas turētājs nodokli par konstatēto alkoholisko dzērienu iztrūkumu (izlaupījumu, zaudējumu, zudumu u.c.), kas radies, taksācijas periodā pārvietojot alkoholiskos dzērienus saskaņā ar šā likuma 15.pantu , iemaksā valsts budžetā 15 dienu laikā pēc taksācijas perioda beigām, ja šajā likumā nav noteikts citādi.\n(9) Licencēts importētājs nodokli par konstatēto alkoholisko dzērienu iztrūkumu (izlaupījumu, zaudējumu, zudumu u.c.), kas radies, ievedot alkoholiskos dzērienus Latvijas Republikas muitas teritorijā to pārvietošanai uz akcīzes preču noliktavu saskaņā ar šā likuma 15.pantu , iemaksā valsts budžetā divu darbdienu laikā no dienas, kad alkoholiskie dzērieni tika ievesti Latvijas Republikas muitas teritorijā, ja šajā likumā nav noteikts citādi.\n(10) Šā likuma 10.panta 8.punktā minētajos gadījumos, kā arī par konstatēto alkoholisko dzērienu iztrūkumu šā likuma 15. 1 pantā minētajos gadījumos nodokli maksā atbilstoši Muitas likumam vai citiem attiecīgiem normatīvajiem aktiem.\n(11) Šā likuma 10.panta 9.punktā minētajos gadījumos nodokli maksā atbilstoši šā likuma 16.panta noteikumiem."
    },
    {
      "provision_ref": "Art. 12",
      "chapter": "III nodaļa. Nodokļa aprēķināšana un maksāšana",
      "section": "12",
      "title": "Nodokļa deklarācija",
      "content": "(1) Nodokļa deklarāciju par taksācijas periodu licencēts importētājs vai noliktavas turētājs iesniedz Valsts ieņēmumu dienestam 15 dienu laikā pēc attiecīgā taksācijas perioda beigām.\n(2) Noliktavas turētājs iesniedz nodokļa deklarāciju par katru akcīzes preču noliktavu atsevišķi.\n(3) Nodokļa deklarācijas veidlapu apstiprina Ministru kabinets."
    },
    {
      "provision_ref": "Art. 13",
      "chapter": "III nodaļa. Nodokļa aprēķināšana un maksāšana",
      "section": "13",
      "title": "Akcīzes nodokļa marku izsniegšana un saņemšana",
      "content": "(1) Akcīzes nodokļa markas izsniedz Valsts ieņēmumu dienests.\n(2) Akcīzes nodokļa markas var saņemt:\n1) licencēti importētāji;\n2) noliktavu turētāji.\n(3) Saņemot akcīzes nodokļa markas, licencēts importētājs vai noliktavas turētājs šā likuma 14.pantā paredzētajā kārtībā iesniedz nodrošinājumu par nodokļa apmēru, kas atbilst izsniegto akcīzes nodokļa marku daudzumam, ja šajā likumā nav noteikts citādi.\n(3 1 ) Alkoholiskajiem dzērieniem, par kuriem ir izsniegtas akcīzes nodokļa markas, piemēro atlikto nodokļa maksāšanu līdz brīdim, kad par tiem samaksā nodokli saskaņā ar šo likumu.\n(4) Ja licencēts importētājs vai noliktavas turētājs atdod Valsts ieņēmumu dienestam saņemtās, bet neizmantotās vai bojātās akcīzes nodokļa markas, to iegādes izdevumus sedz licencēts importētājs vai noliktavas turētājs, kas saņēmis šīs akcīzes nodokļa markas, izņemot šā panta sestajā un devītajā daļā minētos gadījumus.\n(5) Atdotās akcīzes nodokļa markas ir iznīcināmas, izņemot tās, kuras ir akcīzes nodokļa marku ražotājuzņēmuma oriģināliepakojumā. Izdevumus, kas saistīti ar atdoto akcīzes nodokļa marku iznīcināšanu, sedz licencēts importētājs vai noliktavas turētājs, kas atdevis akcīzes nodokļa markas, izņemot šā panta sestajā daļā minēto gadījumu.\n(6) Ja Valsts ieņēmumu dienests licencētam importētājam vai noliktavas turētājam izsniedzis bojātas vai nederīgas akcīzes nodokļa markas, šā panta ceturtajā un piektajā daļā minētie izdevumi licencētam importētājam vai noliktavas turētājam nav jāsedz. Valsts ieņēmumu dienests atdotās bojātās vai nederīgās akcīzes nodokļa markas apmaina pret jaunām akcīzes nodokļa markām.\n( 7) Ja licencēts importētājs vai noliktavas turētājs atdod taksācijas periodā saņemtās, bet neizmantotās vai bojātās akcīzes nodokļa markas Valsts ieņēmumu dienestam 15 dienu laikā pēc taksācijas perioda beigām, nodoklis, kas aprēķināts atbilstoši saņemtajām akcīzes nodokļa markām, attiecīgam licencētam importētājam vai noliktavas turētājam nav jāmaksā.\n(8) Ja licencēts importētājs vai noliktavas turētājs atdod Valsts ieņēmumu dienestam saņemtās, bet neizmantotās vai bojātās akcīzes nodokļa markas, par kurām nodoklis ir samaksāts, samaksātais nodoklis tiek pārskaitīts turpmākajiem nodokļa maksājumiem vai pēc attiecīgā licencēta importētāja vai noliktavas turētāja rakstveida pieprasījuma tiek atmaksāts 15 dienu laikā. Attiecīgais licencēts importētājs vai noliktavas turētājs sedz šā panta ceturtajā un piektajā daļā minētos izdevumus.\n(9) Ja licencēts importētājs vai noliktavas turētājs atdod saņemtās, bet neizmantotās akcīzes nodokļa markas to ražotājuzņēmuma oriģināliepakojumā, šā panta ceturtajā un piektajā daļā minētie izdevumi licencētam importētājam vai noliktavas turētājam nav jāsedz."
    },
    {
      "provision_ref": "Art. 14",
      "chapter": "III nodaļa. Nodokļa aprēķināšana un maksāšana",
      "section": "14",
      "title": "Nodrošinājumi",
      "content": "(1) Lai veiktu darbības ar alkoholiskajiem dzērieniem un izmantotu atlikto nodokļa maksāšanu, licencēts importētājs un noliktavas turētājs iesniedz nodrošinājumu šajā pantā noteiktajā kārtībā.\n(2) Nodrošinājums nedrīkst būt mazāks par nodokli, kas aprēķināts par attiecīgo alkoholisko dzērienu daudzumu, ar kuru tiks veiktas darbības, piemērojot atlikto nodokļa maksāšanu, izņemot šā panta trešajā un ceturtajā daļā minētos gadījumus.\n(2 1 ) Nodrošinājumu atbilstoši aprēķinātajam nodoklim pēc šā likuma 7.panta pirmajā daļā noteiktajām nodokļa likmēm iesniedz par alkoholiskajiem dzērieniem:\n1) par kuriem maksā nodokli saskaņā ar šā likuma 11.panta trešās daļas 2.punktu un piekto daļu;\n2) kuri atrodas akcīzes preču noliktavā un kuriem piemēro atlikto nodokļa maksāšanu (izņemot šīs daļas 1.punktā minētos alkoholiskos dzērienus);\n3) kuriem piemēro atlikto nodokļa maksāšanu saskaņā ar šā likuma 15.pantu .\n(2 2 ) Nodrošinājumu iesniedz neatkarīgi no tā, vai minētie alkoholiskie dzērieni tiks atbrīvoti no nodokļa, tiks izmantoti citu alkoholisko dzērienu ražošanā vai arī nodoklis netiks maksāts citu iemeslu dēļ. Minētais nosacījums attiecas arī uz spirtu vai uz jebkuru citu alkoholisko dzērienu, kuru izmanto kā izejvielu alkoholisko dzērienu ražošanā.\n(3) Ministru kabinets paredz nosacījumus, kuru izpildes gadījumā noliktavas turētājam, kas ražo alkoholiskos dzērienus, var tikt samazināts nodrošinājuma lielums.\n(4) (Izslēgta ar 12.12.2002 . likumu)\n(5) Licencēts importētājs vai noliktavas turētājs var iesniegt šādus nodrošinājumus:\n1) vienreizēju nodrošinājumu, kas paredzēts aprēķinātā nodokļa parāda vienam noteiktam apjomam;\n2) vispārēju nodrošinājumu, kas paredzēts noteiktam laika periodam un aprēķinātā nodokļa parāda noteiktam apjomam.\n(6) Par nodrošinājumu var izmantot:\n1) drošības naudu;\n2) saistības izpildes apdrošināšanas polisi;\n3) kredītiestādes galvojumu;\n4) ķīlas līgumu, ko noliktavas turētājs vai licencēts importētājs noslēdzis ar Valsts ieņēmumu dienestu.\n(7) Ja attiec īgs licencēts importētājs vai noliktavas turētājs, kas atdod taksācijas periodā saņemtās, bet neizmantotās vai bojātās akcīzes nodokļa markas Valsts ieņēmumu dienestam 15 dienu laikā pēc taksācijas perioda beigām, pirms akcīzes nodokļa marku saņemšanas ir iesniedzis vienreizēju nodrošinājumu, kurš aprēķināts atbilstoši izsniegtajām akcīzes nodokļa markām, tad nodrošinājums, kas atbilst nodokļa summai, kuru nosaka atbilstoši atdotajām akcīzes nodokļa markām, tiek dzēsts vai atdots iesniedzējam pēc šā likuma 13.panta ceturtajā un piektajā daļā minēto izdevumu segšanas.\n(8) Kārtību, kādā iesniedzami, dzēšami un atdodami nodrošinājumi, nosaka Ministru kabinets."
    },
    {
      "provision_ref": "Art. 15",
      "chapter": "III nodaļa. Nodokļa aprēķināšana un maksāšana",
      "section": "15",
      "title": "Atliktās nodokļa maksāšanas piemērošana, pārvietojot alkoholiskos dzērienus",
      "content": "(1) Licencētam importētājam šajā likumā noteiktajā kārtībā atļauts atlikto nodokļa maksāšanu piemērot aprēķinātajam nodoklim par alkoholiskajiem dzērieniem, kurus ieved Latvijas Republikas muitas teritorijā to pārvietošanai uz akcīzes preču noliktavu.\n(2) Noliktavas turētājam atļauts atlikto nodokļa maksāšanu piemērot aprēķinātajam nodoklim par alkoholiskajiem dzērieniem, kurus:\n1) no vienas akcīzes preču noliktavas pārvieto uz citu akcīzes preču noliktavu;\n2) izved no akcīzes preču noliktavas to tālākai izvešanai no Latvijas Republikas muitas teritorijas;\n3) ieved Latvijas Republikas muitas teritorijā to pārvietošanai uz akcīzes preču noliktavu.\n(2 1 ) Šā panta otrās daļas 1.punktā minētajā gadījumā nodrošinājumu atbilstoši šā likuma 14.pantam iesniedz akcīzes preču noliktavas turētājs — alkoholisko dzērienu nosūtītājs. Akcīzes preču noliktavas turētājs — alkoholisko dzērienu nosūtītājs — var neiesniegt nodrošinājumu, ja to iesniedz akcīzes preču noliktavas turētājs — alkoholisko dzērienu saņēmējs.\n(3) Licencēts importētājs, kas veic šā panta pirmajā daļā minētās darbības, un noliktavas turētājs, kas veic šā panta otrajā daļā minētās darbības, nemaksā aprēķināto nodokli, ja Valsts ieņēmumu dienestam iesniedz dokumentus, kas apliecina, ka alkoholiskie dzērieni atbilst vienam no šādiem nosacījumiem:\n1) tie ir saņemti akcīzes preču noliktavā;\n2) tie ir izvesti no Latvijas Republikas muitas teritorijas.\n(4) Licencēts importētājs par alkoholiskajiem dzērieniem, kurus pārvieto saskaņā ar šā panta pirmo daļu, divu darbdienu laikā, skaitot no dienas, kad alkoholiskie dzērieni tika ievesti Latvijas Republikas muitas teritorijā, iesniedz šā panta trešajā daļā minētos dokumentus vai samaksā aprēķināto nodokli atbilstoši šā likuma 7.pantā noteiktajai likmei.\n(5) Noliktavas turētājs, kas saskaņā ar šā panta 2.1 daļu iesniedzis nodrošinājumu par alkoholiskajiem dzērieniem, kurus taksācijas periodā pārvieto saskaņā ar šā panta otro daļu, 15 dienu laikā pēc taksācijas perioda beigām iesniedz šā panta trešajā daļā minētos dokumentus vai samaksā aprēķināto nodokli atbilstoši šā likuma 7.pantā noteiktajai likmei.\n(6) Ja licencēts importētājs vai noliktavas turētājs par šā panta pirmajā vai otrajā daļā minētajām darbībām neiesniedz nodrošinājumu atbilstoši šā likuma prasībām, atlikto nodokļa maksāšanu nepiemēro un licencēts importētājs vai noliktavas turētājs maksā nodokli atbilstoši šā likuma 7.pantā noteiktajai likmei."
    },
    {
      "provision_ref": "Art. 15.1",
      "chapter": "III nodaļa. Nodokļa aprēķināšana un maksāšana",
      "section": "15.1",
      "title": "15. 1 pants. Atliktās nodokļa maksāšanas piemērošana Muitas likumā un citos attiecīgos normatīvajos aktos noteiktajos gadījumos",
      "content": "(1) Atliktā nodokļa maksāšana attiecas arī uz alkoholiskajiem dzērieniem, kuriem piemēro attiecīgu muitas procedūru (izņemot izlaišanu brīvam apgrozījumam) tajos gadījumos, kad nodokli nemaksā saskaņā ar Muitas likumu vai citiem attiecīgiem normatīvajiem aktiem.\n(2) Ja šā panta pirmajā daļā minētās muitas procedūras netiek izpildītas, atbildīgā persona samaksā nodokli pēc šā likuma 7.pantā noteiktās likmes.\n(3) Šā panta pirmajā daļā minētajā gadījumā par attiecīgajiem alkoholiskajiem dzērieniem šā likuma 14.pantā minēto nodrošinājumu neiesniedz."
    },
    {
      "provision_ref": "Art. 16",
      "chapter": "IV nodaļa. Atbildība un alkoholisko dzērienu inventarizācija",
      "section": "16",
      "title": "Atbildība par šā likuma pārkāpumiem",
      "content": "(1) Atbildību par šā likuma pārkāpumiem nosaka šis likums un likums “Par nodokļiem un nodevām”.\n(1 1 ) Latvijas Republikas muitas teritorijā aizliegts ražot, pārstrādāt, uzglabāt, pārvietot un realizēt alkoholiskos dzērienus, par kuriem nav samaksāts akcīzes nodoklis vai kuri nav marķēti ar akcīzes nodokļa markām, izņemot šajā likumā noteiktos gadījumus.\n(2) Attiecīgajām valsts uzraudzības un kontroles iestādēm ir tiesības normatīvajos aktos noteiktajā kārtībā konfiscēt alkoholiskos dzērienus, kuri ievesti Latvijas Republikas muitas teritorijā vai izvesti no akcīzes preču noliktavas, bet par kuriem nav samaksāts nodoklis un nav iesniegts šā likuma 14.pantā noteiktais nodrošinājums par minēto darbību izpildi vai kuri tiek uzglabāti, pārvietoti un realizēti Latvijas Republikas muitas teritorijā bez akcīzes nodokļa markām, izņemot šā likuma 5.panta ceturtajā daļā minētos gadījumus.\n(2 1 ) Alkoholisko dzērienu konfiskācija par šā likuma vai citu normatīvo aktu pārkāpumiem vai citu normatīvo aktu piemērošana attiecībā uz pārkāpumiem alkoholisko dzērienu aprites jomā neatbrīvo attiecīgo personu no saistībām samaksāt nodokli saskaņā ar šo likumu un soda naudu saskaņā ar likumu “Par nodokļiem un nodevām”.\n(3) Konfiscētie alkoholiskie dzērieni ir iznīcināmi, pārstrādājami vai denaturējami Ministru kabineta noteiktajā kārtībā.\n(4) Ja persona veic jebkuras darbības ar alkoholiskajiem dzērieniem, neievērojot šā likuma noteikumus (tajā skaitā veic alkoholisko dzērienu nedeklarētu vai citādu ievešanu valstī, neievērojot normatīvajos aktos noteikto ievešanas kārtību vai neizpildot attiecīgās muitas procedūras, veic alkoholisko dzērienu nereģistrētu vai citādu ražošanu, neievērojot normatīvajos aktos noteikto kārtību, kādā atļauts ražot alkoholiskos dzērienus, veic jebkuras citas darbības ar alkoholiskajiem dzērieniem, par kuriem nav samaksāts nodoklis vai nav iesniegts šā likuma 14.pantā noteiktais nodrošinājums vai kuri nav marķēti ar akcīzes nodokļa markām saskaņā ar šo likumu), Valsts ieņēmumu dienests bezstrīdus kārtībā piedzen valsts budžetā atbilstoši šā likuma 7.pantā noteiktajām likmēm nenomaksātās nodokļa summas un soda naudu saskaņā ar likumu “Par nodokļiem un nodevām”.\n(5) Šā panta ceturtajā daļā minētajos gadījumos Valsts ieņēmumu dienests nodokli aprēķina pēc likmēm, kas bija spēkā dienā, kad minētās darbības tika veiktas. Ja to nevar noteikt, nodokli aprēķina pēc likmēm, kas ir spēkā dienā, kad minētās darbības konstatētas.\n(6) Ja cita valsts iestāde, nevis Valsts ieņēmumu dienests atbilstoši savai kompetencei konstatē, ka persona ir veikusi šā panta ceturtajā daļā minētās darbības, attiecīgā valsts iestāde par to rakstveidā informē (ne vēlāk kā triju darbdienu laikā) Valsts ieņēmumu dienestu. Valsts ieņēmumu dienests piedzen nodokli un soda naudu saskaņā ar šā panta ceturto un piekto daļu.\n(7) Šā panta ceturtajā daļā minētajos gadījumos nodokli un soda naudu piedzen no personas, kuras valdījumā ir alkoholiskie dzērieni, ar kuriem veiktas šā panta ceturtajā daļā minētās darbības, vai no personas, kas veikusi šā panta ceturtajā daļā minētās darbības, ja netiek konstatēts minēto alkoholisko dzērienu valdītājs.\n(8) Alkoholiskos dzērienus, kurus atbrīvo no nodokļa saskaņā ar šā likuma 8.pantu , aizliegts izmantot citiem mērķiem (nekā noteiktajam atbrīvojumam) vai nodot personai, kurai nav tiesību tos saņemt.\n(9) Ja šā panta astotā daļa netiek ievērota, par minētajiem alkoholiskajiem dzērieniem maksājams nodoklis un soda nauda šajā pantā noteiktajā kārtībā. Nodokli un soda naudu piedzen no personas, kura ir saņēmusi no nodokļa atbrīvotus alkoholiskos dzērienus un nav ievērojusi šā panta astotajā daļā vai attiecīgajos Ministru kabineta noteikumos paredzēto kārtību, kādā minētajiem alkoholiskajiem dzērieniem atļauts piemērot atbrīvojumu no nodokļa saskaņā ar šā likuma 8.pantu . Šī daļa neattiecas uz šā likuma 8.panta ceturtajā daļā minētajiem gadījumiem."
    },
    {
      "provision_ref": "Art. 17",
      "chapter": "IV nodaļa. Atbildība un alkoholisko dzērienu inventarizācija",
      "section": "17",
      "title": "Alkoholisko dzērienu inventarizācija",
      "content": "(1) Noliktavas turētājs inventarizē alkoholiskos dzērienus, kas atrodas akcīzes preču noliktavā, pēc stāvokļa uz pēctaksācijas perioda pirmo datumu.\n(2) Inventarizācijas rezultāti uzrādāmi grāmatvedības reģistros un nodokļa deklarācijā šajā likumā noteiktajā termiņā.\n(3) Ja inventarizācijā tiek konstatēta grāmatvedības reģistru un inventarizācijas datu atšķirība, novērtējumu starpība — pārpalikums vai iztrūkums (izlaupījums, zaudējums, zudums u.c.) — uzrādāma gan grāmatvedības reģistros, gan nodokļa deklarācijā, ievērojot šādu kārtību:\n1) ja inventarizācijā konstatē pārpalikumu, to apliek ar nodokli atbilstoši šā likuma 7.pantā noteiktajai likmei;\n2) ja inventarizācijā konstatē iztrūkumu, to apliek ar nodokli atbilstoši šā likuma 7.pantā noteiktajai likmei, izņemot iztrūkumu, kas:\na) atbilst Ministru kabineta apstiprinātajām normām,\nb) radies šā likuma 8.panta pirmās daļas 3.punktā minēto zaudējumu rezultātā."
    },
    {
      "provision_ref": "PN 1",
      "chapter": "IV nodaļa. Atbildība un alkoholisko dzērienu inventarizācija",
      "section": "pn1",
      "title": "1. Šā likuma 5.panta otrā daļa, ceturtās daļas 2.punkts un 6.panta pirmā un otrā daļa attiecībā uz alkoholisko dzērienu ražošanas uzņēmumiem, kas saņēmuši speciālu atļauju (licenci) alkoholisko dzērienu izgatavošanai un realizācijai, piemērojama, sākot ar 1999.gada 1.jūliju.",
      "content": "1. Šā likuma 5.panta otrā daļa, ceturtās daļas 2.punkts un 6.panta pirmā un otrā daļa attiecībā uz alkoholisko dzērienu ražošanas uzņēmumiem, kas saņēmuši speciālu atļauju (licenci) alkoholisko dzērienu izgatavošanai un realizācijai, piemērojama, sākot ar 1999.gada 1.jūliju."
    },
    {
      "provision_ref": "PN 2",
      "chapter": "IV nodaļa. Atbildība un alkoholisko dzērienu inventarizācija",
      "section": "pn2",
      "title": "2. Līdz 1999.gada 30.jūnijam alkoholisko dzērienu ražošanas uzņēmumi, kas saņēmuši speciālu atļauju (licenci) alkoholisko dzērienu izgatavošanai un realizācijai:",
      "content": "1) ir nodokļa maksātāji un drīkst saņemt akcīzes nodokļa markas saskaņā ar šā likuma 13.panta otro daļu;\n2) nodokli par katras pagājušās dekādes faktisko apgrozījumu samaksā kārtējā mēneša 13. un 23.datumā un nākamā mēneša 3.datumā, bet ne vēlāk kā 30 dienu laikā no akcīzes nodokļa marku saņemšanas dienas;\n3) nemaksā nodokli (iesniedzot nodrošinājumu) par saražoto produkciju, kuru izved:\na) uz akcīzes preču noliktavu,\nb) no Latvijas Republikas muitas teritorijas,\nc) uz muitas noliktavu."
    },
    {
      "provision_ref": "PN 3",
      "chapter": "IV nodaļa. Atbildība un alkoholisko dzērienu inventarizācija",
      "section": "pn3",
      "title": "3. Ministru kabinets līdz 2003.gadam izstrādā šā likuma grozījumus, lai šā likuma 1. , 8. un 9.pantu saskaņotu ar attiecīgajām Eiropas Savienības prasībām.",
      "content": "3. Ministru kabinets līdz 2003.gadam izstrādā šā likuma grozījumus, lai šā likuma 1. , 8. un 9.pantu saskaņotu ar attiecīgajām Eiropas Savienības prasībām."
    },
    {
      "provision_ref": "PN 4",
      "chapter": "IV nodaļa. Atbildība un alkoholisko dzērienu inventarizācija",
      "section": "pn4",
      "title": "4. Šā likuma 7.panta otrā daļa stājas spēkā 2000.gada 1.janvārī.",
      "content": "4. Šā likuma 7.panta otrā daļa stājas spēkā 2000.gada 1.janvārī."
    },
    {
      "provision_ref": "PN 5",
      "chapter": "IV nodaļa. Atbildība un alkoholisko dzērienu inventarizācija",
      "section": "pn5",
      "title": "5. Šajā likumā lietotās atsauces uz Latvijas kombinētās nomenklatūras kodiem atbilst Latvijas kombinētās nomenklatūras 2003.gada versijai.",
      "content": "( 12.12.2002 . likuma redakcijā, kas stājas spēkā 01.01.2003. )\n( 12.12.2002 . likuma redakcijā, kas stājas spēkā 01.01.2003. )"
    }
  ],
  "definitions": [
    {
      "term": "alkoholiskie dzērieni",
      "definition": "vīns, raudzētie dzērieni, starpprodukti un pārējie alkoholiskie dzērieni, kas minēti šīs daļas 5.punktā",
      "source_provision": "Art. 1"
    },
    {
      "term": "starpprodukti",
      "definition": "produkti (izņemot vīnu un raudzētos dzērienus), kuri atbilst Latvijas kombinētās nomenklatūras kodiem 2204, 2205 un 2206, ja vien to pamatizejviela ir vīns vai raudzētie dzērieni un faktiskais spirta daudzums tajos pārsniedz 1,2 tilpumprocentus, bet nepārsniedz 22 tilpumprocentus. Gatavā starpprodukta sastāvā esošais spirts var nebūt tikai raudzētas izcelsmes, ja vismaz 30 procenti no faktiskā spirta daudzuma tilpumprocentiem ir raudzētas izcelsmes",
      "source_provision": "Art. 1"
    },
    {
      "term": "akcīzes nodokļa marka",
      "definition": "Valsts ieņēmumu dienesta izdota īpaša alkoholisko dzērienu akcīzes nodokļa marka, kas tiek piestiprināta alkoholisko dzērienu pudelei (vai citam fasējumam) un apliecina, ka ar akcīzes nodokļa markām marķētie alkoholiskie dzērieni ir ņemti valsts kontrolē a t bilstoši alkoholiskajiem dzērieniem noteiktā akcīzes nodokļa samaksas nosacījumiem un alkoholiskajiem dzērieniem ir legāla izcelsme",
      "source_provision": "Art. 1"
    },
    {
      "term": "akcīzes preču noliktava",
      "definition": "alkoholisko dzērienu akcīzes preču noliktava — Valsts ieņēmumu dienesta kontrolēta vieta, kur noliktavas turētājs ražo, pārstrādā, uzglabā, ieved, saņem vai nosūta alkoholiskos dzērienus, piemērojot atlikto nodokļa maksāšanu saskaņā ar šā likuma nosacījumiem",
      "source_provision": "Art. 1"
    },
    {
      "term": "noliktavas turētājs",
      "definition": "akcīzes preču noliktavas turētājs — juridiskā persona, kurai ir Valsts ieņēmumu dienesta atļauja turēt akcīzes preču noliktavu un kuras īpašumā vai valdījumā ir akcīzes preču noliktava",
      "source_provision": "Art. 1"
    },
    {
      "term": "licencēts importētājs",
      "definition": "juridiskā persona, kura Alkohola aprites likumā noteiktajā kārtībā saņēmusi speciālu atļauju (licenci) alkoholisko dzērienu ievešanai Latvijas Republikas muitas teritorijā izlaišanai brīvam apgrozījumam un kurai nav noliktavas turētāja statusa",
      "source_provision": "Art. 1"
    },
    {
      "term": "atliktā nodokļa maksāšana",
      "definition": "akcīzes nodokļa samaksas atlikšana, ievērojot šā likuma nosacījumus attiecībā uz alkoholisko dzērienu ražošanu, pārstrādi, uzglabāšanu un pārvadāšanu.",
      "source_provision": "Art. 1"
    }
  ]
}